Part 1 - ALU/alu.v
// Computer Architecture (CO224) - Lab 05 - Part 1
// Design: ALU
// Group Number : 27
// E Numbers : E/18/077, E/18/227
// Names : Dharmarathne N.S., Mudalige D.H.
// Date: 09 January 2022

/**********************************************************************************/
// Define the FORWARD module
module forwardForALU(DATA2, RESULT);
	// Port declarations
	input [7:0] DATA2;
	output [7:0] RESULT;
	assign #1 RESULT=DATA2;
endmodule	// endmodule statement

/**********************************************************************************/
// Define the ADD module
module addForALU(DATA1, DATA2, RESULT);
	// Port declarations
	input [7:0] DATA1, DATA2;
	output [7:0] RESULT;
	assign #2 RESULT=DATA1 + DATA2;
endmodule	// endmodule statement

/**********************************************************************************/
// Define the AND module
module andForALU(DATA1, DATA2, RESULT);
	// Port declarations
	input [7:0] DATA1, DATA2;
	output [7:0] RESULT;
	assign #1 RESULT=DATA1 & DATA2;
endmodule	// endmodule statement

/**********************************************************************************/
// Define the OR module
module orForALU(DATA1, DATA2, RESULT);
	// Port declarations
	input [7:0] DATA1, DATA2;
	output [7:0] RESULT;
	assign #1 RESULT=DATA1 | DATA2;
endmodule	// endmodule statement

/**********************************************************************************/
// ALU 8-bit module 
module alu(DATA1, DATA2, SELECT, RESULT);
	// Port declarations, Declarations of wire & reg
	input [7:0] DATA1, DATA2;
	input [2:0] SELECT;
	output reg [7:0] RESULT;
	wire [7:0] RESULT_FOR_FORWARD, RESULT_FOR_ADD, RESULT_FOR_AND, RESULT_FOR_OR;
	
	// Instantiate modules
	forwardForALU forward_1(DATA2, RESULT_FOR_FORWARD);
	addForALU add_1(DATA1, DATA2, RESULT_FOR_ADD);
	andForALU and_1(DATA1, DATA2, RESULT_FOR_AND);
	orForALU or_1(DATA1, DATA2, RESULT_FOR_OR);

	// Select everytime DATA1, DATA2, SELECT updates
	always @(DATA1, DATA2, SELECT)
	begin
		// Select the function to implement using a case structure
		case(SELECT)
			3'b000:	//FORWARD
				assign RESULT=RESULT_FOR_FORWARD;
			3'b001:	//ADD
				assign RESULT=RESULT_FOR_ADD;
			3'b010:	//AND
				assign RESULT=RESULT_FOR_AND;
			3'b011:	//OR
				assign RESULT=RESULT_FOR_OR;
			default: RESULT=8'b00000000;	//DEFAULT
		endcase
	end
endmodule	// endmodule statement

Part 1 - ALU/alu_tb.v
// Computer Architecture (CO224) - Lab 05 - Part 1
// Design: ALU - Testbench
// Group Number : 27
// E Numbers : E/18/077, E/18/227
// Names : Dharmarathne N.S., Mudalige D.H.
// Date: 09 January 2022

/**********************************************************************************/
// Define the stimulus module
module alu_tb;
	// Declarations of reg & wire
    reg [7:0] OPERAND1,OPERAND2;
	reg [2:0] ALUOP;
    wire [7:0] ALURESULT;
	
	// Instantiate module
	// In this case, instantiate alu
    alu myalu(OPERAND1,OPERAND2, ALUOP, ALURESULT);

	// Behavioural block, initial
    initial
    begin
	  // To display the results
      $monitor($time," OPERAND1: %b, OPERAND2: %b, ALUOP: %b, ALURESULT: %b",OPERAND1,OPERAND2,ALUOP,ALURESULT);
      $dumpfile("wavedata.vcd");
      $dumpvars(0,myalu);
    end

    initial
    begin
	  ALUOP = 3'b000;
      OPERAND1= 8'b00000111;
      OPERAND2= 8'b00111011;
	  
	  #5
	  ALUOP = 3'b001;
	  OPERAND1= 8'b00000001;
      OPERAND2= 8'b00000011;
	  
	  #5
	  ALUOP = 3'b010;
      OPERAND1= 8'b01010001;
      OPERAND2= 8'b01110011;
	  
	  #5
	  ALUOP = 3'b011;
      OPERAND1= 8'b01100101;
      OPERAND2= 8'b00110011;
    end
endmodule	// endmodule statement

Part 1 - ALU/wavedata.vcd
$date
	Thu Mar 16 16:43:15 2023
$end
$version
	Icarus Verilog
$end
$timescale
	1s
$end
$scope module alu_tb $end
$scope module myalu $end
$var wire 8 ! DATA1 [7:0] $end
$var wire 8 " DATA2 [7:0] $end
$var wire 8 # RESULT_FOR_ADD [7:0] $end
$var wire 8 $ RESULT_FOR_AND [7:0] $end
$var wire 8 % RESULT_FOR_FORWARD [7:0] $end
$var wire 8 & RESULT_FOR_OR [7:0] $end
$var wire 3 ' SELECT [2:0] $end
$var reg 8 ( RESULT [7:0] $end
$scope module forward_1 $end
$var wire 8 ) DATA2 [7:0] $end
$var wire 8 * RESULT [7:0] $end
$upscope $end
$scope module add_1 $end
$var wire 8 + DATA1 [7:0] $end
$var wire 8 , DATA2 [7:0] $end
$var wire 8 - RESULT [7:0] $end
$upscope $end
$scope module and_1 $end
$var wire 8 . DATA1 [7:0] $end
$var wire 8 / DATA2 [7:0] $end
$var wire 8 0 RESULT [7:0] $end
$upscope $end
$scope module or_1 $end
$var wire 8 1 DATA1 [7:0] $end
$var wire 8 2 DATA2 [7:0] $end
$var wire 8 3 RESULT [7:0] $end
$upscope $end
$upscope $end
$upscope $end
$enddefinitions $end
#0
$dumpvars
bz 3
b111011 2
b111 1
bz 0
b111011 /
b111 .
bx -
b111011 ,
b111 +
bx *
b111011 )
bx (
b0 '
bz &
bx %
bz $
bx #
b111011 "
b111 !
$end
#1
b111111 &
b111111 3
b11 $
b11 0
b111011 %
b111011 *
b111011 (
#2
b1000010 #
b1000010 -
#5
b1000010 (
b11 "
b11 )
b11 ,
b11 /
b11 2
b1 !
b1 +
b1 .
b1 1
b1 '
#6
b1 $
b1 0
b11 &
b11 3
b11 %
b11 *
#7
b100 #
b100 -
b100 (
#10
b1 (
b1110011 "
b1110011 )
b1110011 ,
b1110011 /
b1110011 2
b1010001 !
b1010001 +
b1010001 .
b1010001 1
b10 '
#11
b1010001 $
b1010001 0
b1010001 (
b1110011 &
b1110011 3
b1110011 %
b1110011 *
#12
b11000100 #
b11000100 -
#15
b1110011 (
b110011 "
b110011 )
b110011 ,
b110011 /
b110011 2
b1100101 !
b1100101 +
b1100101 .
b1100101 1
b11 '
#16
b100001 $
b100001 0
b1110111 &
b1110111 3
b1110111 (
b110011 %
b110011 *
#17
b10011000 #
b10011000 -
